odoo/addons/website_event_sale_b2x_alt_price/README.rst
odoo/addons/website_event_sale_b2x_alt_price/__init__.py
odoo/addons/website_event_sale_b2x_alt_price/__manifest__.py
odoo/addons/website_event_sale_b2x_alt_price/i18n/it.po
odoo/addons/website_event_sale_b2x_alt_price/i18n/website_event_sale_b2x_alt_price.pot
odoo/addons/website_event_sale_b2x_alt_price/models/__init__.py
odoo/addons/website_event_sale_b2x_alt_price/models/event_ticket.py
odoo/addons/website_event_sale_b2x_alt_price/readme/CONTRIBUTORS.rst
odoo/addons/website_event_sale_b2x_alt_price/readme/DESCRIPTION.rst
odoo/addons/website_event_sale_b2x_alt_price/readme/ROADMAP.rst
odoo/addons/website_event_sale_b2x_alt_price/readme/USAGE.rst
odoo/addons/website_event_sale_b2x_alt_price/static/description/icon.png
odoo/addons/website_event_sale_b2x_alt_price/static/description/index.html
odoo/addons/website_event_sale_b2x_alt_price/templates/website_event_sale.xml
odoo12_addon_website_event_sale_b2x_alt_price-12.0.1.0.0.99.dev6.dist-info/METADATA
odoo12_addon_website_event_sale_b2x_alt_price-12.0.1.0.0.99.dev6.dist-info/WHEEL
odoo12_addon_website_event_sale_b2x_alt_price-12.0.1.0.0.99.dev6.dist-info/top_level.txt
odoo12_addon_website_event_sale_b2x_alt_price-12.0.1.0.0.99.dev6.dist-info/RECORD
